django_enquiries-0.2.2.dist-info/licenses/LICENSE
enquiries/__init__.py
enquiries/admin.py
enquiries/apps.py
enquiries/forms.py
enquiries/models.py
enquiries/signals.py
enquiries/tests.py
enquiries/views.py
enquiries/migrations/__init__.py
enquiries/templates/enquiries/email.html
enquiries/templates/enquiries/email.txt
enquiries/templates/enquiries/form.html
django_enquiries-0.2.2.dist-info/METADATA
django_enquiries-0.2.2.dist-info/WHEEL
django_enquiries-0.2.2.dist-info/top_level.txt
django_enquiries-0.2.2.dist-info/RECORD
