Metadata-Version: 2.4
Name: django-enquiries
Version: 0.2.2
Summary: A Django app to handle un-authenticated user enquiries via a contuct-us form.
Author-email: Egide Ndazimana <egide.n1997@gmail.com>
License-Expression: MIT
Project-URL: Repository, https://github.com/egiden/django-enquiries.git
Classifier: Environment :: Web Environment
Classifier: Framework :: Django
Classifier: Framework :: Django :: 5.1
Classifier: Intended Audience :: Developers
Classifier: Programming Language :: Python
Classifier: Programming Language :: Python :: 3
Classifier: Programming Language :: Python :: 3 :: Only
Classifier: Programming Language :: Python :: 3.10
Classifier: Programming Language :: Python :: 3.11
Classifier: Programming Language :: Python :: 3.12
Classifier: Operating System :: OS Independent
Requires-Python: >=3.10
License-File: LICENSE
Requires-Dist: django>=5.1
Dynamic: license-file
